Python/Comparative_condition.py
Python/Single_Condition.py
Python/__init__.py
Python/generate_report.py
Python/lrobject.py
Python/plot.py
Python/test.py
Python/utils.py
crosstalke-0.1.0.dist-info/METADATA
crosstalke-0.1.0.dist-info/WHEEL
crosstalke-0.1.0.dist-info/RECORD
