Metadata-Version: 2.1
Name: CrossTalke
Version: 0.1.0
Summary: 
Author: CostaLab
Requires-Python: >=3.11,<4.0
Classifier: Programming Language :: Python :: 3
Classifier: Programming Language :: Python :: 3.11
Classifier: Programming Language :: Python :: 3.12
Requires-Dist: adjustText (>=1.2.0,<2.0.0)
Requires-Dist: matplotlib (>=3.9.1,<4.0.0)
Requires-Dist: networkx (>=3.3,<4.0)
Requires-Dist: numpy (>=2.0.1,<3.0.0)
Requires-Dist: pandas (>=2.2.2,<3.0.0)
Requires-Dist: plotnine (>=0.13.6,<0.14.0)
Requires-Dist: requests (>=2.32.3,<3.0.0)
Requires-Dist: scikit-learn (>=1.5.1,<2.0.0)
Requires-Dist: seaborn (>=0.13.2,<0.14.0)
